README.txt
setup.py
linkzilla/__init__.py
linkzilla/settings.py
linkzilla/version.py
linkzilla.egg-info/PKG-INFO
linkzilla.egg-info/SOURCES.txt
linkzilla.egg-info/dependency_links.txt
linkzilla.egg-info/top_level.txt
linkzilla/base/__init__.py
linkzilla/base/client.py
linkzilla/base/provider.py
linkzilla/base/storage.py
linkzilla/django/__init__.py
linkzilla/django/context_processors.py
linkzilla/django/management/__init__.py
linkzilla/django/management/commands/__init__.py
linkzilla/django/management/commands/linkzilla_update.py
linkzilla/lib/__init__.py
linkzilla/lib/phpserialize.py
linkzilla/services/__init__.py
linkzilla/services/linkfeed/__init__.py
linkzilla/services/linkfeed/client.py
linkzilla/services/linkfeed/provider.py
linkzilla/services/sape/__init__.py
linkzilla/services/sape/client.py
linkzilla/services/sape/provider.py
linkzilla/storages/__init__.py
linkzilla/storages/dbm.py
linkzilla/storages/orm/__init__.py
linkzilla/storages/orm/admin.py
linkzilla/storages/orm/models.py