Metadata-Version: 1.0
Name: linkzilla
Version: 0.1.5
Summary: Client library to link trade services (sape.ru, linkfeed.ru)
Home-page: http://bitbucket.org/lorien/linkzilla
Author: Grigoriy Petukhov
Author-email: lorien@lorien.name
License: BSD
Keywords: django application sape.ru linkfeed.ru
Platform: UNKNOWN
Classifier: Development Status :: 4 - Beta
Classifier: Environment :: Web Environment
Classifier: Framework :: Django
Classifier: Intended Audience :: Developers
Classifier: License :: OSI Approved :: BSD License
Classifier: Operating System :: OS Independent
Classifier: Programming Language :: Python
Classifier: Topic :: Utilities
